setup.py
appoints/__init__.py
appoints/appoint.py
appoints/io.py
appoints/special.py
appoints.egg-info/PKG-INFO
appoints.egg-info/SOURCES.txt
appoints.egg-info/dependency_links.txt
appoints.egg-info/requires.txt
appoints.egg-info/top_level.txt