Metadata-Version: 1.0
Name: appoints
Version: 1.1a2
Summary: A Library for managing appointments
Home-page: https://github.com/PH111P/appoints
Author: Philip Wellnitz
Author-email: philipwellnitz@gmx.de
License: UNKNOWN
Platform: UNKNOWN
